inmanta_plugins/user/__init__.py
inmanta_plugins/user/setup.cfg
inmanta_plugins/user/model/_init.cf
inmanta_plugins/user/templates/groupadd.j2
inmanta_plugins/user/templates/useradd.j2
inmanta_module_user-0.1.23.dist-info/METADATA
inmanta_module_user-0.1.23.dist-info/WHEEL
inmanta_module_user-0.1.23.dist-info/top_level.txt
inmanta_module_user-0.1.23.dist-info/RECORD
