Metadata-Version: 2.1
Name: inmanta-module-user
Version: 0.1.23
License: ASL 2
Requires-Dist: inmanta-module-exec
Requires-Dist: inmanta-module-std
